moves_cli/__init__.py
moves_cli/core/components/chunk_producer.py
moves_cli/core/components/section_producer.py
moves_cli/core/components/similarity_calculator.py
moves_cli/core/components/similarity_units/phonetic.py
moves_cli/core/components/similarity_units/semantic.py
moves_cli/core/presentation_controller.py
moves_cli/core/settings_editor.py
moves_cli/core/speaker_manager.py
moves_cli/data/llm_instruction.md
moves_cli/data/ml_models/all-MiniLM-L6-v2_quint8_avx2/config.json
moves_cli/data/ml_models/all-MiniLM-L6-v2_quint8_avx2/model.onnx
moves_cli/data/ml_models/all-MiniLM-L6-v2_quint8_avx2/special_tokens_map.json
moves_cli/data/ml_models/all-MiniLM-L6-v2_quint8_avx2/tokenizer.json
moves_cli/data/ml_models/all-MiniLM-L6-v2_quint8_avx2/tokenizer_config.json
moves_cli/data/ml_models/nemo-streaming-stt-480ms-int8/decoder.int8.onnx
moves_cli/data/ml_models/nemo-streaming-stt-480ms-int8/encoder.int8.onnx
moves_cli/data/ml_models/nemo-streaming-stt-480ms-int8/joiner.int8.onnx
moves_cli/data/ml_models/nemo-streaming-stt-480ms-int8/tokens.txt
moves_cli/data/models.py
moves_cli/data/settings_template.toml
moves_cli/main.py
moves_cli/utils/data_handler.py
moves_cli/utils/id_generator.py
moves_cli/utils/model_preparer.py
moves_cli/utils/text_normalizer.py
moves_cli-1.2.0.dist-info/WHEEL
moves_cli-1.2.0.dist-info/entry_points.txt
moves_cli-1.2.0.dist-info/METADATA
moves_cli-1.2.0.dist-info/RECORD
