Metadata-Version: 2.3
Name: moves-cli
Version: 1.2.0
Summary: Presentation control, reimagined.
Author: mdonmez
Author-email: mdonmez <124686256+mdonmez@users.noreply.github.com>
License: GNU General Public License v3.0
Requires-Dist: fastembed>=0.7.3
Requires-Dist: httpx>=0.28.1
Requires-Dist: instructor[litellm]>=1.11.3
Requires-Dist: jellyfish>=1.2.0
Requires-Dist: litellm>=1.79.3
Requires-Dist: num2words>=0.5.14
Requires-Dist: numpy>=2.3.3
Requires-Dist: pydantic>=2.12.0
Requires-Dist: pymupdf>=1.26.5
Requires-Dist: pynput>=1.8.1
Requires-Dist: rapidfuzz>=3.14.1
Requires-Dist: rich>=14.2.0
Requires-Dist: sherpa-onnx>=1.12.14
Requires-Dist: sounddevice>=0.5.2
Requires-Dist: tomlkit>=0.13.3
Requires-Dist: typer>=0.19.2
Requires-Dist: unidecode>=1.4.0
Requires-Dist: xxhash>=3.6.0
Requires-Python: >=3.13
Project-URL: Documentation, https://github.com/mdonmez/moves-cli/tree/master/docs
Project-URL: Homepage, https://github.com/mdonmez/moves-cli
